{
  "date": "2026-05-20",
  "picks": [
    {
      "slug": "websketch-ir",
      "reason": "Featured Tool",
      "signals": [
        "popular"
      ]
    },
    {
      "slug": "synthesis",
      "reason": "Composable tool framework for building complex AI workflows",
      "signals": [
        "popular"
      ]
    },
    {
      "slug": "backpropagate",
      "reason": "Structured feedback loops for improving AI behavior through iteration",
      "signals": [
        "featured"
      ]
    },
    {
      "slug": "accessibility-suite",
      "reason": "Unified monorepo for accessibility testing, evidence generation, and WCAG compliance tooling",
      "signals": [
        "popular"
      ]
    },
    {
      "slug": "mcp-stress-test",
      "reason": "Load and stress testing utilities for MCP servers and tool ecosystems",
      "signals": [
        "popular"
      ]
    },
    {
      "slug": "audiobooker",
      "reason": "Audio book generation and management system",
      "signals": [
        "popular"
      ]
    }
  ]
}